squarem_jaxopt/__init__.py
squarem_jaxopt/squarem_jaxopt.py
squarem_jaxopt-0.1.3.dist-info/licenses/LICENSE
squarem_jaxopt-0.1.3.dist-info/METADATA
squarem_jaxopt-0.1.3.dist-info/WHEEL
squarem_jaxopt-0.1.3.dist-info/top_level.txt
squarem_jaxopt-0.1.3.dist-info/RECORD
