Metadata-Version: 2.4
Name: squarem-jaxopt
Version: 0.1.3
Summary: SQUAREM accelerator for JAXopt solvers
Requires-Python: >=3.11
License-File: LICENSE
Requires-Dist: jax>=0.7.1
Requires-Dist: jaxopt>=0.8.5
Dynamic: license-file
